Script started on Fri Apr 17 23:28:48 2015
[1m[7m%[27m[1m[0m                                                                                                                                                                    ]2;marko@markos-MacBook-Pro: ~/tmp]1;~/tmp[0m[27m[24m[J[38;5;117m~/tmp[00m [38;5;012m[38;5;133m [00m[38;5;077má…[00m [K[?1h=ggit clone git@github.com:marko-asplund/blog-gists.git[?1l>
]2;git clone git@github.com:marko-asplund/blog-gists.git]1;gitCloning into 'blog-gists'...
remote: Counting objects: 58, done.[K
remote: Compressing objects:   4% (1/23)   [Kremote: Compressing objects:   8% (2/23)   [Kremote: Compressing objects:  13% (3/23)   [Kremote: Compressing objects:  17% (4/23)   [Kremote: Compressing objects:  21% (5/23)   [Kremote: Compressing objects:  26% (6/23)   [Kremote: Compressing objects:  30% (7/23)   [Kremote: Compressing objects:  34% (8/23)   [Kremote: Compressing objects:  39% (9/23)   [Kremote: Compressing objects:  43% (10/23)   [Kremote: Compressing objects:  47% (11/23)   [Kremote: Compressing objects:  52% (12/23)   [Kremote: Compressing objects:  56% (13/23)   [Kremote: Compressing objects:  60% (14/23)   [Kremote: Compressing objects:  65% (15/23)   [Kremote: Compressing objects:  69% (16/23)   [Kremote: Compressing objects:  73% (17/23)   [Kremote: Compressing objects:  78% (18/23)   [Kremote: Compressing objects:  82% (19/23)   [Kremote: Compressing objects:  86% (20/23)   [Kremote: Compressing objects:  91% (21/23)   [Kremote: Compressing objects:  95% (22/23)   [Kremote: Compressing objects: 100% (23/23)   [Kremote: Compressing objects: 100% (23/23), done.[K
remote: Total 58 (delta 6), reused 0 (delta 0), pack-reused 3[K
Receiving objects:   1% (1/58)   Receiving objects:   3% (2/58)   Receiving objects:   5% (3/58)   Receiving objects:   6% (4/58)   Receiving objects:   8% (5/58)   Receiving objects:  10% (6/58)   Receiving objects:  12% (7/58)   Receiving objects:  13% (8/58)   Receiving objects:  15% (9/58)   Receiving objects:  17% (10/58)   Receiving objects:  18% (11/58)   Receiving objects:  20% (12/58)   Receiving objects:  22% (13/58)   Receiving objects:  24% (14/58)   Receiving objects:  25% (15/58)   Receiving objects:  27% (16/58)   Receiving objects:  29% (17/58)   Receiving objects:  31% (18/58)   Receiving objects:  32% (19/58)   Receiving objects:  34% (20/58)   Receiving objects:  36% (21/58)   Receiving objects:  37% (22/58)   Receiving objects:  39% (23/58)   Receiving objects:  41% (24/58)   Receiving objects:  43% (25/58)   Receiving objects:  44% (26/58)   Receiving objects:  46% (27/58)   Receiving objects:  48% (28/58)   Receiving objects:  50% (29/58)   Receiving objects:  51% (30/58)   Receiving objects:  53% (31/58)   Receiving objects:  55% (32/58)   Receiving objects:  56% (33/58)   Receiving objects:  58% (34/58)   Receiving objects:  60% (35/58)   Receiving objects:  62% (36/58)   Receiving objects:  63% (37/58)   Receiving objects:  65% (38/58)   Receiving objects:  67% (39/58)   Receiving objects:  68% (40/58)   Receiving objects:  70% (41/58)   Receiving objects:  72% (42/58)   Receiving objects:  74% (43/58)   Receiving objects:  75% (44/58)   Receiving objects:  77% (45/58)   Receiving objects:  79% (46/58)   Receiving objects:  81% (47/58)   Receiving objects:  82% (48/58)   Receiving objects:  84% (49/58)   Receiving objects:  86% (50/58)   Receiving objects:  87% (51/58)   Receiving objects:  89% (52/58)   Receiving objects:  91% (53/58)   Receiving objects:  93% (54/58)   Receiving objects:  94% (55/58)   Receiving objects:  96% (56/58)   Receiving objects:  98% (57/58)   Receiving objects: 100% (58/58)   Receiving objects: 100% (58/58), 4.14 KiB | 0 bytes/s, done.
Resolving deltas:   0% (0/6)   Resolving deltas:  33% (2/6)   Resolving deltas:  50% (3/6)   Resolving deltas:  66% (4/6)   Resolving deltas:  83% (5/6)   Resolving deltas: 100% (6/6)   Resolving deltas: 100% (6/6), done.
Checking connectivity... done.
[1m[7m%[27m[1m[0m                                                                                                                                                                    ]2;marko@markos-MacBook-Pro: ~/tmp]1;~/tmpcd blog-gists/macros-interop

git checkout macros-interop/fail
[0m[27m[24m[J[38;5;117m~/tmp[00m [38;5;012m[38;5;133m [00m[38;5;077má…[00m [K[?1h=ccd blog-gists/macros-interop[?1l>
]2;cd blog-gists/macros-interop]1;cd[1m[7m%[27m[1m[0m                                                                                                                                                                    ]2;marko@markos-MacBook-Pro: ~/tmp/blog-gists/macros-interop]1;..acros-interop[0m[27m[24m[J[38;5;117m~/tmp/blog-gists/macros-interop[00m [38;5;012m(master [38;5;118mâœ”[38;5;012m)[38;5;133m [00m[38;5;077má…[00m [K[?1h=[?1l>
[1m[7m%[27m[1m[0m                                                                                                                                                                    ]2;marko@markos-MacBook-Pro: ~/tmp/blog-gists/macros-interop]1;..acros-interop[0m[27m[24m[J[38;5;117m~/tmp/blog-gists/macros-interop[00m [38;5;012m(master [38;5;118mâœ”[38;5;012m)[38;5;133m [00m[38;5;077má…[00m [K[?1h=ggit checkout macros-interop/fail[?1l>
]2;git checkout macros-interop/fail]1;gitBranch macros-interop/fail set up to track remote branch macros-interop/fail from origin.
Switched to a new branch 'macros-interop/fail'
[1m[7m%[27m[1m[0m                                                                                                                                                                    ]2;marko@markos-MacBook-Pro: ~/tmp/blog-gists/macros-interop]1;..acros-interop[0m[27m[24m[J[38;5;117m~/tmp/blog-gists/macros-interop[00m [38;5;012m(macros-interop/fail [38;5;118mâœ”[38;5;012m)[38;5;133m [00m[38;5;077má…[00m [K[?1h=ssbt 'runMain com.practicingtechie.gist.macros.JavaClient'[?1l>
]2;sbt 'runMain com.practicingtechie.gist.macros.JavaClient']1;sbt[0m[[0minfo[0m] [0mLoading global plugins from /Users/marko/.sbt/0.13/plugins[0m
[0m[[0minfo[0m] [0mLoading project definition from /Users/marko/tmp/blog-gists/macros-interop/project[0m
javap -c -cp target/scala-2.11/classes com.practicingtechie.gist.macros.MyReusableService$
[0m[[0minfo[0m] [0mSet current project to macros-interop (in build file:/Users/marko/tmp/blog-gists/macros-interop/)[0m
[0m[[0minfo[0m] [0mUpdating {file:/Users/marko/tmp/blog-gists/macros-interop/}mymacros...[0m
[0m[[0minfo[0m] [0mResolving org.scala-lang#scala-library;2.11.6 ...[0m
[A[2K[0m[[0minfo[0m] [0mResolving org.scala-lang#scala-reflect;2.11.6 ...[0m
[A[2K[0m[[0minfo[0m] [0mResolving org.scala-lang#scala-compiler;2.11.6 ...[0m
[A[2K[0m[[0minfo[0m] [0mResolving org.scala-lang.modules#scala-xml_2.11;1.0.3 ...[0m
[A[2K[0m[[0minfo[0m] [0mResolving org.scala-lang.modules#scala-parser-combinators_2.11;1.0.3 ...[0m
[A[2K[0m[[0minfo[0m] [0mResolving jline#jline;2.12.1 ...[0m
[0m[[0minfo[0m] [0mDone updating.[0m
[0m[[0minfo[0m] [0mUpdating {file:/Users/marko/tmp/blog-gists/macros-interop/}root...[0m
[0m[[0minfo[0m] [0mResolving org.scala-lang#scala-library;2.11.6 ...[0m
[A[2K[0m[[0minfo[0m] [0mResolving com.practicingtechie#mymacros_2.11;0.1 ...[0m
[A[2K[0m[[0minfo[0m] [0mResolving org.scala-lang#scala-reflect;2.11.6 ...[0m
[A[2K[0m[[0minfo[0m] [0mResolving com.typesafe.scala-logging#scala-logging-slf4j_2.11;2.1.2 ...[0m
[A[2K[0m[[0minfo[0m] [0mResolving com.typesafe.scala-logging#scala-logging-api_2.11;2.1.2 ...[0m
[A[2K[0m[[0minfo[0m] [0mResolving org.slf4j#slf4j-api;1.7.7 ...[0m
[A[2K[0m[[0minfo[0m] [0mResolving ch.qos.logback#logback-classic;1.1.3 ...[0m
[A[2K[0m[[0minfo[0m] [0mResolving ch.qos.logback#logback-core;1.1.3 ...[0m
[A[2K[0m[[0minfo[0m] [0mResolving org.scala-lang#scala-compiler;2.11.6 ...[0m
[A[2K[0m[[0minfo[0m] [0mResolving org.scala-lang.modules#scala-xml_2.11;1.0.3 ...[0m
[A[2K[0m[[0minfo[0m] [0mResolving org.scala-lang.modules#scala-parser-combinators_2.11;1.0.3 ...[0m
[A[2K[0m[[0minfo[0m] [0mResolving jline#jline;2.12.1 ...[0m
[0m[[0minfo[0m] [0mDone updating.[0m
[0m[[0minfo[0m] [0mCompiling 1 Scala source to /Users/marko/tmp/blog-gists/macros-interop/mymacros/target/scala-2.11/classes...[0m
[0m[[0minfo[0m] [0mCompiling 2 Scala sources and 1 Java source to /Users/marko/tmp/blog-gists/macros-interop/target/scala-2.11/classes...[0m
performing macro expansion MyReusableService.macroMethod at source-/Users/marko/tmp/blog-gists/macros-interop/src/main/scala/com/practicingtechie/gist/macros/ScalaClient.scala,line-7,offset=158
println("Hello macro world")
Apply(Ident(TermName("println")), List(Literal(Constant("Hello macro world"))))
[0m[[33mwarn[0m] [0mthere was one deprecation warning; re-run with -deprecation for details[0m
[0m[[33mwarn[0m] [0mone warning found[0m
[0m[[31merror[0m] [0m/Users/marko/tmp/blog-gists/macros-interop/src/main/java/com/practicingtechie/gist/macros/JavaClient.java:6: cannot find symbol[0m
[0m[[31merror[0m] [0m  symbol:   method macroMethod()[0m
[0m[[31merror[0m] [0m  location: class com.practicingtechie.gist.macros.MyReusableService[0m
[0m[[31merror[0m] [0mMyReusableService.macroMethod[0m
[0m[[31merror[0m] [0m(root/compile:[31mcompileIncremental[0m) javac returned nonzero exit code[0m
[0m[[31merror[0m] [0mTotal time: 3 s, completed Apr 17, 2015 11:29:19 PM[0m
[1m[7m%[27m[1m[0m                                                                                                                                                                    ]2;marko@markos-MacBook-Pro: ~/tmp/blog-gists/macros-interop]1;..acros-interop[0m[27m[24m[J[38;5;117m~/tmp/blog-gists/macros-interop[00m [38;5;012m(macros-interop/fail [38;5;118mâœ”[38;5;012m)[38;5;133m [00m[38;5;077má…[00m [K[?1h=jjavap -c -cp target/scala-2.11/classes com.practicingtechie.gist.macros.MyReusableService$[?1l>
]2;javap -c -cp target/scala-2.11/classes ]1;javapCompiled from "MyReusableService.scala"
public final class com.practicingtechie.gist.macros.MyReusableService$ {
  public static final com.practicingtechie.gist.macros.MyReusableService$ MODULE$;

  public static {};
    Code:
       0: new           #2                  // class com/practicingtechie/gist/macros/MyReusableService$
       3: invokespecial #12                 // Method "<init>":()V
       6: return

  public void regularMethod();
    Code:
       0: getstatic     #18                 // Field scala/Predef$.MODULE$:Lscala/Predef$;
       3: ldc           #20                 // String foobar
       5: invokevirtual #24                 // Method scala/Predef$.println:(Ljava/lang/Object;)V
       8: return
}
[1m[7m%[27m[1m[0m                                                                                                                                                                    ]2;marko@markos-MacBook-Pro: ~/tmp/blog-gists/macros-interop]1;..acros-interop[0m[27m[24m[J[38;5;117m~/tmp/blog-gists/macros-interop[00m [38;5;012m(macros-interop/fail [38;5;118mâœ”[38;5;012m)[38;5;133m [00m[38;5;077má…[00m [K[?1h=ggit checkout master[?1l>
]2;git checkout master]1;gitSwitched to branch 'master'
Your branch is up-to-date with 'origin/master'.
[1m[7m%[27m[1m[0m                                                                                                                                                                    ]2;marko@markos-MacBook-Pro: ~/tmp/blog-gists/macros-interop]1;..acros-interop[0m[27m[24m[J[38;5;117m~/tmp/blog-gists/macros-interop[00m [38;5;012m(master [38;5;118mâœ”[38;5;012m)[38;5;133m [00m[38;5;077má…[00m [K[?1h=ssbt 'runMain com.practicingtechie.gist.macros.JavaClient'[?1l>
]2;sbt 'runMain com.practicingtechie.gist.macros.JavaClient']1;sbt[0m[[0minfo[0m] [0mLoading global plugins from /Users/marko/.sbt/0.13/plugins[0m
[0m[[0minfo[0m] [0mLoading project definition from /Users/marko/tmp/blog-gists/macros-interop/project[0m
[0m[[0minfo[0m] [0mSet current project to macros-interop (in build file:/Users/marko/tmp/blog-gists/macros-interop/)[0m
[0m[[0minfo[0m] [0mCompiling 1 Scala source to /Users/marko/tmp/blog-gists/macros-interop/mymacros/target/scala-2.11/classes...[0m
performing macro expansion c.universe.Quasiquote(scala.StringContext.apply("println(\"Hello macro world\")")).q.apply[Any]() at source-/Users/marko/tmp/blog-gists/macros-interop/mymacros/src/main/scala/com/practicingtechie/gist/macros/MyMacros.scala,line-9,offset=222
c.universe.internal.reificationSupport.SyntacticApplied(c.universe.internal.reificationSupport.SyntacticTermIdent(c.universe.TermName("println"), false), scala.collection.immutable.List(scala.collection.immutable.List(c.universe.Literal(c.universe.Constant("Hello macro world")))))
Apply(Select(Select(Select(Select(Ident(TermName("c")), TermName("universe")), TermName("internal")), TermName("reificationSupport")), TermName("SyntacticApplied")), List(Apply(Select(Select(Select(Select(Ident(TermName("c")), TermName("universe")), TermName("internal")), TermName("reificationSupport")), TermName("SyntacticTermIdent")), List(Apply(Select(Select(Ident(TermName("c")), TermName("universe")), TermName("TermName")), List(Literal(Constant("println")))), Literal(Constant(false)))), Apply(Select(Select(Select(Ident(TermName("scala")), TermName("collection")), TermName("immutable")), TermName("List")), List(Apply(Select(Select(Select(Ident(TermName("scala")), TermName("collection")), TermName("immutable")), TermName("List")), List(Apply(Select(Select(Ident(TermName("c")), TermName("universe")), TermName("Literal")), List(Apply(Select(Select(Ident(TermName("c")), TermName("universe")), TermName("Constant")), List(Literal(Constant("Hello macro world"))))))))))))
performing macro expansion `package`.this.materializeWeakTypeTag[Unit](c.universe) at source-/Users/marko/tmp/blog-gists/macros-interop/mymacros/src/main/scala/com/practicingtechie/gist/macros/MyMacros.scala,line-9,offset=221
c.universe.WeakTypeTag.Unit
Select(Select(Select(Ident(TermName("c")), TermName("universe")), TermName("WeakTypeTag")), TermName("Unit"))
[0m[[0minfo[0m] [0mCompiling 2 Scala sources and 1 Java source to /Users/marko/tmp/blog-gists/macros-interop/target/scala-2.11/classes...[0m
performing macro expansion MyReusableService.macroMethod at source-/Users/marko/tmp/blog-gists/macros-interop/src/main/scala/com/practicingtechie/gist/macros/ScalaClient.scala,line-7,offset=158
println("Hello macro world")
Apply(Ident(TermName("println")), List(Literal(Constant("Hello macro world"))))
[0m[[0minfo[0m] [0mRunning com.practicingtechie.gist.macros.JavaClient [0m
foobar
[0m[[32msuccess[0m] [0mTotal time: 3 s, completed Apr 17, 2015 11:29:42 PM[0m
[1m[7m%[27m[1m[0m                                                                                                                                                                    ]2;marko@markos-MacBook-Pro: ~/tmp/blog-gists/macros-interop]1;..acros-interop[0m[27m[24m[J[38;5;117m~/tmp/blog-gists/macros-interop[00m [38;5;012m(master [38;5;118mâœ”[38;5;012m)[38;5;133m [00m[38;5;077má…[00m [K[?1h=ssbt 'runMain com.practicingtechie.gist.macros.ScalaClient'[?1l>
]2;sbt 'runMain com.practicingtechie.gist.macros.ScalaClient']1;sbt[0m[[0minfo[0m] [0mLoading global plugins from /Users/marko/.sbt/0.13/plugins[0m
[0m[[0minfo[0m] [0mLoading project definition from /Users/marko/tmp/blog-gists/macros-interop/project[0m
[0m[[0minfo[0m] [0mSet current project to macros-interop (in build file:/Users/marko/tmp/blog-gists/macros-interop/)[0m
[0m[[0minfo[0m] [0mRunning com.practicingtechie.gist.macros.ScalaClient [0m
foobar
Hello macro world
[0m[[32msuccess[0m] [0mTotal time: 0 s, completed Apr 17, 2015 11:29:47 PM[0m
[1m[7m%[27m[1m[0m                                                                                                                                                                    ]2;marko@markos-MacBook-Pro: ~/tmp/blog-gists/macros-interop]1;..acros-interop[0m[27m[24m[J[38;5;117m~/tmp/blog-gists/macros-interop[00m [38;5;012m(master [38;5;118mâœ”[38;5;012m)[38;5;133m [00m[38;5;077má…[00m [K[?1h=jjavap -c -cp target/scala-2.11/classes com.practicingtechie.gist.macros.MyReusableService$[?1l>
]2;javap -c -cp target/scala-2.11/classes ]1;javapCompiled from "MyReusableService.scala"
public final class com.practicingtechie.gist.macros.MyReusableService$ {
  public static final com.practicingtechie.gist.macros.MyReusableService$ MODULE$;

  public static {};
    Code:
       0: new           #2                  // class com/practicingtechie/gist/macros/MyReusableService$
       3: invokespecial #12                 // Method "<init>":()V
       6: return

  public void regularMethod();
    Code:
       0: getstatic     #18                 // Field scala/Predef$.MODULE$:Lscala/Predef$;
       3: ldc           #20                 // String foobar
       5: invokevirtual #24                 // Method scala/Predef$.println:(Ljava/lang/Object;)V
       8: return
}
[1m[7m%[27m[1m[0m                                                                                                                                                                    ]2;marko@markos-MacBook-Pro: ~/tmp/blog-gists/macros-interop]1;..acros-interop[0m[27m[24m[J[38;5;117m~/tmp/blog-gists/macros-interop[00m [38;5;012m(master [38;5;118mâœ”[38;5;012m)[38;5;133m [00m[38;5;077má…[00m [K[?1h=jjavap -c -cp target/scala-2.11/classes com.practicingtechie.gist.macros.ScalaClient$[?1l>
]2;javap -c -cp target/scala-2.11/classes ]1;javapCompiled from "ScalaClient.scala"
public final class com.practicingtechie.gist.macros.ScalaClient$ {
  public static final com.practicingtechie.gist.macros.ScalaClient$ MODULE$;

  public static {};
    Code:
       0: new           #2                  // class com/practicingtechie/gist/macros/ScalaClient$
       3: invokespecial #12                 // Method "<init>":()V
       6: return

  public void main(java.lang.String[]);
    Code:
       0: getstatic     #19                 // Field com/practicingtechie/gist/macros/MyReusableService$.MODULE$:Lcom/practicingtechie/gist/macros/MyReusableService$;
       3: invokevirtual #22                 // Method com/practicingtechie/gist/macros/MyReusableService$.regularMethod:()V
       6: getstatic     #27                 // Field scala/Predef$.MODULE$:Lscala/Predef$;
       9: ldc           #29                 // String Hello macro world
      11: invokevirtual #33                 // Method scala/Predef$.println:(Ljava/lang/Object;)V
      14: getstatic     #39                 // Field scala/runtime/BoxedUnit.UNIT:Lscala/runtime/BoxedUnit;
      17: pop
      18: return
}
[1m[7m%[27m[1m[0m                                                                                                                                                                    ]2;marko@markos-MacBook-Pro: ~/tmp/blog-gists/macros-interop]1;..acros-interop[0m[27m[24m[J[38;5;117m~/tmp/blog-gists/macros-interop[00m [38;5;012m(master [38;5;118mâœ”[38;5;012m)[38;5;133m [00m[38;5;077má…[00m [K[?1h=eexit[?1l>
]2;exit]1;exit
Script done on Fri Apr 17 23:29:59 2015
